{
    "products":[
        {
      "id": 1,
      "name": "Asus zenphone max",
      "desc": "4 gb ram with sixteen gb rom",
      "price": 12300,
      "color": "#330250",
      "image":
          "https://www.gadgetshieldz.com/images/detailed/224/Asus_Zenfone_Max_Pro__M1__ZB601KL_Maximum_Protection_Ultra_Clear.png"
        },
        {
            "id": 2,
            "name": "Asus zenphone max",
            "desc": "8 gb ram with sixteen gb rom",
            "price": 12300,
            "color": "#330250",
            "image":"https://rukminim1.flixcart.com/image/312/312/kmds4nk0/computer/t/0/9/na-thin-and-light-laptop-asus-original-imagfabezamstqhz.jpeg?q=70"
         },
         {
         "id": 3,
         "name": "Asus zenphone max",
         "desc": "6 gb ram with sixteen gb rom",
         "price": 12300,
         "color": "#330250",
         "image":
           "https://www.gadgetshieldz.com/images/detailed/224/Asus_Zenfone_Max_Pro__M1__ZB601KL_Maximum_Protection_Ultra_Clear.png"
         },
        {
         "id": 4,
         "name": "Microsoft Laptop",
         "desc": "16 GB  ram with 512 gb rom",
         "price": 12300,
         "color": "#330250",
         "image":"https://images-na.ssl-images-amazon.com/images/I/71h6PpGaz9L._AC_SL1500_.jpg"
          },
         {
         "id": 5,
         "name": "Asus zenphone max",
         "desc": "two gb ram with sixteen gb rom",
         "price": 12300,
         "color": "#330250",
         "image":
           "https://www.gadgetshieldz.com/images/detailed/224/Asus_Zenfone_Max_Pro__M1__ZB601KL_Maximum_Protection_Ultra_Clear.png"
         },
         {
         "id": 6,
         "name": "Asus zenphone max",
         "desc": "two gb ram with sixteen gb rom",
         "price": 12300,
         "color": "#330250",
         "image":
            "https://www.gadgetshieldz.com/images/detailed/224/Asus_Zenfone_Max_Pro__M1__ZB601KL_Maximum_Protection_Ultra_Clear.png"
         },
         {
         "id": 7,
         "name": "Asus zenphone max",
         "desc": "two gb ram with sixteen gb rom",
         "price": 12300,
         "color": "#330250",
         "image":
            "https://www.gadgetshieldz.com/images/detailed/224/Asus_Zenfone_Max_Pro__M1__ZB601KL_Maximum_Protection_Ultra_Clear.png"
        },
        {
        "id": 8,
        "name": "Asus zenphone max",
        "desc": "two gb ram with sixteen gb rom",
        "price": 12300,
        "color": "#330250",
        "image":
            "https://www.gadgetshieldz.com/images/detailed/224/Asus_Zenfone_Max_Pro__M1__ZB601KL_Maximum_Protection_Ultra_Clear.png"
         },
         {
        "id": 9,
        "name": "Asus zenphone max",
        "desc": "two gb ram with sixteen gb rom",
        "price": 12300,
        "color": "#330250",
        "image":
           "https://www.gadgetshieldz.com/images/detailed/224/Asus_Zenfone_Max_Pro__M1__ZB601KL_Maximum_Protection_Ultra_Clear.png"
         }
    ]
}